gerrit_dash_creator/__init__.py
gerrit_dash_creator/cmd/__init__.py
gerrit_dash_creator/cmd/bugs.py
gerrit_dash_creator/cmd/creator.py
gerrit_dash_creator-0.2.0.data/data/share/gerrit-dash-creator/dashboards/all-the-specs.dash
gerrit_dash_creator-0.2.0.data/data/share/gerrit-dash-creator/dashboards/api-wg.dash
gerrit_dash_creator-0.2.0.data/data/share/gerrit-dash-creator/dashboards/chef_watched.dash
gerrit_dash_creator-0.2.0.data/data/share/gerrit-dash-creator/dashboards/cinder-priorities.dash
gerrit_dash_creator-0.2.0.data/data/share/gerrit-dash-creator/dashboards/cinder.dash
gerrit_dash_creator-0.2.0.data/data/share/gerrit-dash-creator/dashboards/compute-drivers.dash
gerrit_dash_creator-0.2.0.data/data/share/gerrit-dash-creator/dashboards/config-core.dash
gerrit_dash_creator-0.2.0.data/data/share/gerrit-dash-creator/dashboards/cross-project.dash
gerrit_dash_creator-0.2.0.data/data/share/gerrit-dash-creator/dashboards/designate-ptl-overview.dash
gerrit_dash_creator-0.2.0.data/data/share/gerrit-dash-creator/dashboards/designate-release.dash
gerrit_dash_creator-0.2.0.data/data/share/gerrit-dash-creator/dashboards/designate.dash
gerrit_dash_creator-0.2.0.data/data/share/gerrit-dash-creator/dashboards/devstack.dash
gerrit_dash_creator-0.2.0.data/data/share/gerrit-dash-creator/dashboards/doc-install-guides.dash
gerrit_dash_creator-0.2.0.data/data/share/gerrit-dash-creator/dashboards/doc.dash
gerrit_dash_creator-0.2.0.data/data/share/gerrit-dash-creator/dashboards/gate-changes.dash
gerrit_dash_creator-0.2.0.data/data/share/gerrit-dash-creator/dashboards/glance.dash
gerrit_dash_creator-0.2.0.data/data/share/gerrit-dash-creator/dashboards/heat.dash
gerrit_dash_creator-0.2.0.data/data/share/gerrit-dash-creator/dashboards/horizon-related-repos.dash
gerrit_dash_creator-0.2.0.data/data/share/gerrit-dash-creator/dashboards/horizon-stable.dash
gerrit_dash_creator-0.2.0.data/data/share/gerrit-dash-creator/dashboards/horizon.dash
gerrit_dash_creator-0.2.0.dist-info/AUTHORS
gerrit_dash_creator-0.2.0.dist-info/LICENSE
gerrit_dash_creator-0.2.0.dist-info/METADATA
gerrit_dash_creator-0.2.0.dist-info/WHEEL
gerrit_dash_creator-0.2.0.dist-info/entry_points.txt
gerrit_dash_creator-0.2.0.dist-info/pbr.json
gerrit_dash_creator-0.2.0.dist-info/top_level.txt
gerrit_dash_creator-0.2.0.dist-info/RECORD
