Metadata-Version: 2.1
Name: gerrit-dash-creator
Version: 0.2.0
Summary: Gerrit Dashboard Creator
Home-page: https://opendev.org/x/gerrit-dash-creator
Author: OpenStack
Author-email: openstack-discuss@lists.openstack.org
License: UNKNOWN
Platform: UNKNOWN
Classifier: Environment :: OpenStack
Classifier: Intended Audience :: Information Technology
Classifier: Intended Audience :: System Administrators
Classifier: License :: OSI Approved :: Apache Software License
Classifier: Operating System :: POSIX :: Linux
Classifier: Programming Language :: Python
Classifier: Programming Language :: Python :: 3
Classifier: Programming Language :: Python :: 3.6
Classifier: Programming Language :: Python :: 3.7
Requires-Dist: jinja2
Requires-Dist: pbr (>=1.6)
Requires-Dist: simplejson (>=2.2.0)
